{
	"products": [{
		"Id": "100000000",
		"City": "New York",
		"Area": "Brooklyn",
		"Quarter": "Crown Heights",
		"Image": "1.jpg",
		"Longitude": "",
		"Latitude": "",
		"risk": "75.4%",
		"profile": "1",
		"powerzone": "Power zone 213",
		"prevOutages": "9",
		"alertedCust": "YES",
		"status": "EMERGENCY",
		"alertedRepairMan": "YES"
	}, {
		"Id": "100000000",
		"City": "New York",
		"Area": "Queens",
		"Quarter": "Richmond hill",
		"Image": "2.jpg",
		"Longitude": "",
		"Latitude": "",
		"risk": "71.4%",
		"profile": "1",
		"powerzone": "Power zone 214",
		"prevOutages": "9",
		"alertedCust": "YES",
		"status": "EMERGENCY",
		"alertedRepairMan": "YES"
	}, {
		"Id": "100000000",
		"City": "New York",
		"Area": "Brooklyn",
		"Quarter": "Park Slope",
		"Image": "3.jpg",
		"Longitude": "",
		"Latitude": "",
		"risk": "55.7%",
		"profile": "3",
		"powerzone": "Power zone 791",
		"prevOutages": "7",
		"alertedCust": "NO",
		"status": "BE AWARE",
		"alertedRepairMan": "YES"
	}, {
		"Id": "100000000",
		"City": "New York",
		"Area": "Bronx",
		"Quarter": "Fordham Heights",
		"Image": "4.jpg",
		"Longitude": "",
		"Latitude": "",
		"risk": "42.4%",
		"profile": "4",
		"powerzone": "Power zone 746",
		"prevOutages": "6",
		"alertedCust": "NO",
		"status": "SAFE",
		"alertedRepairMan": "NO"

	}, {
		"Id": "100000000",
		"City": "New York",
		"Area": "Brooklyn",
		"Quarter": "Bedford-Stuyvesant",
		"Image": "5.jpg",
		"Longitude": "",
		"Latitude": "",
		"risk": "33.7%",
		"profile": "5",
		"powerzone": "Power zone 751",
		"prevOutages": "5",
		"alertedCust": "NO",
		"status": "CALM",
		"alertedRepairMan": "NO"
	}, {
		"Id": "100000000",
		"City": "New York",
		"Area": "Manhattan",
		"Quarter": "Upper West Side",
		"Image": "6.jpg",
		"Longitude": "",
		"Latitude": "",
		"risk": "61.9%",
		"profile": "2",
		"powerzone": "Power zone 781",
		"prevOutages": "8",
		"alertedCust": "YES",
		"status": "HIGH ALERT",
		"alertedRepairMan": "YES"
	}, {
		"Id": "100000000",
		"City": "New York",
		"Area": "Manhattan",
		"Quarter": "Upper East Side",
		"Image": "7.jpg",
		"Longitude": "",
		"Latitude": "",
		"risk": "41.6%",
		"profile": "4",
		"powerzone": "Power zone 917",
		"prevOutages": "6",
		"alertedCust": "NO",
		"status": "BE AWARE",
		"alertedRepairMan": "NO"

	}, {
		"Id": "100000000",
		"City": "New York",
		"Area": "Brooklyn",
		"Quarter": "Bushwick",
		"Image": "8.jpg",
		"Longitude": "",
		"Latitude": "",
		"risk": "59.4%",
		"profile": "3",
		"powerzone": "Power zone 319",
		"prevOutages": "7",
		"alertedCust": "NO",
		"status": "BE AWARE",
		"alertedRepairMan": "YES"
	}, {
		"Id": "100000000",
		"City": "New York",
		"Area": "Queens",
		"Quarter": "Forest Hills",
		"Image": "9.jpg",
		"Longitude": "",
		"Latitude": "",
		"risk": "73.8%",
		"profile": "1",
		"powerzone": "Power zone 914",
		"prevOutages": "9",
		"alertedCust": "YES",
		"status": "EMERGENCY",
		"alertedRepairMan": "YES"

	}, {
		"Id": "100000000",
		"City": "New York",
		"Area": "Queens",
		"Quarter": "Jamaica",
		"Image": "10.jpg",
		"Longitude": "",
		"Latitude": "",
		"risk": "49.5%",
		"profile": "4",
		"powerzone": "Power zone 516",
		"prevOutages": "6",
		"alertedCust": "NO",
		"status": "SAFE",
		"alertedRepairMan": "NO"
	}, {
		"Id": "100000000",
		"City": "New York",
		"Area": "Queens",
		"Quarter": "Flushing",
		"Image": "11.jpg",
		"Longitude": "",
		"Latitude": "",
		"risk": "23.7%",
		"profile": "5",
		"powerzone": "Power zone 817",
		"prevOutages": "5",
		"alertedCust": "NO",
		"status": "CALM",
		"alertedRepairMan": "NO"
	}, {
		"Id": "100000000",
		"City": "New York",
		"Area": "Manhattan",
		"Quarter": "Midtown",
		"Image": "12.jpg",
		"Longitude": "",
		"Latitude": "",
		"risk": "80.3%",
		"profile": "1",
		"powerzone": "Power zone 213",
		"prevOutages": "9",
		"alertedCust": "YES",
		"status": "EMERGENCY",
		"alertedRepairMan": "YES"

	}, {
		"Id": "100000000",
		"City": "New York",
		"Area": "Bronx",
		"Quarter": "Parkchester",
		"Image": "13.jpg",
		"Longitude": "",
		"Latitude": "",
		"risk": "50.6%",
		"profile": "3",
		"powerzone": "Power zone 102",
		"prevOutages": "7",
		"alertedCust": "NO",
		"status": "EMERGENCY",
		"alertedRepairMan": "YES"
	}, {
		"Id": "100000000",
		"City": "New York",
		"Area": "Brooklyn",
		"Quarter": "Sheepshead Bay",
		"Image": "14.jpg",
		"Longitude": "",
		"Latitude": "",
		"risk": "60.4%",
		"profile": "2",
		"powerzone": "Power zone 901",
		"prevOutages": "8",
		"alertedCust": "YES",
		"status": "SEVERE",
		"alertedRepairMan": "YES"
	}]
}